socktools
