Metadata-Version: 1.0
Name: socktools
Version: 0.2
Summary: A library for dealing with message-based network protocols
Home-page: https://github.com/GarethNelson/python-sock-tools
Author: Gareth Nelson
Author-email: gareth@garethnelson.com
License: GPLv2
Keywords: sockets networking messages
Platform: UNKNOWN
